telethon_asyncpg/__init__.py
telethon_asyncpg/_patch.py
telethon_asyncpg/client/auth.py
telethon_asyncpg/client/downloads.py
telethon_asyncpg/client/telegrambaseclient.py
telethon_asyncpg/client/updates.py
telethon_asyncpg/client/users.py
telethon_asyncpg/network/mtprotosender.py
telethon_asyncpg/sessions/__init__.py
telethon_asyncpg/sessions/abstract.py
telethon_asyncpg/sessions/asyncpg.py
telethon_asyncpg/sessions/base.py
telethon_asyncpg-0.2.0.dist-info/LICENSE
telethon_asyncpg-0.2.0.dist-info/WHEEL
telethon_asyncpg-0.2.0.dist-info/METADATA
telethon_asyncpg-0.2.0.dist-info/RECORD
