Metadata-Version: 2.1
Name: telethon-asyncpg
Version: 0.2.0
Summary: Asyncpg powered session for pgsql databases
Home-page: https://github.com/ukinti/telethon_asyncpg
License: MIT
Keywords: telegram,telethon,mtproto,asyncio,asyncpg
Author: mpa
Author-email: mpa@snejugal.ru
Requires-Python: >=3.7,<4.0
Classifier: Framework :: AsyncIO
Classifier: Intended Audience :: Developers
Classifier: License :: OSI Approved :: MIT License
Classifier: Programming Language :: Python :: 3
Classifier: Programming Language :: Python :: 3.7
Classifier: Programming Language :: Python :: 3.8
Classifier: Programming Language :: Python :: 3.9
Classifier: Topic :: Software Development :: Libraries :: Application Frameworks
Requires-Dist: Telethon (>=1.13.0,<2.0.0)
Requires-Dist: asyncpg (>=0.20.1,<0.21.0)
Project-URL: Repository, https://github.com/ukinti/telethon_asyncpg
